limbus/__init__.py
limbus/core/__init__.py
limbus/core/app.py
limbus/core/async_utils.py
limbus/core/component.py
limbus/core/param.py
limbus/core/params.py
limbus/core/pipeline.py
limbus/core/states.py
limbus/widgets/__init__.py
limbus/widgets/types.py
limbus/widgets/viz.py
limbus/widgets/widget_component.py
limbus_config/__init__.py
limbus_config/config.py
limbus-0.1.6.dist-info/LICENSE
limbus-0.1.6.dist-info/METADATA
limbus-0.1.6.dist-info/WHEEL
limbus-0.1.6.dist-info/top_level.txt
limbus-0.1.6.dist-info/RECORD
