Metadata-Version: 2.1
Name: limbus
Version: 0.1.6
Summary: High level interface to create Pytorch Graphs.
Home-page: https://github.com/kornia/limbus
Author: Luis Ferraz
License-File: LICENSE
Requires-Dist: typeguard (<3.0.0)
Provides-Extra: components
Requires-Dist: limbus-components ; extra == 'components'
Provides-Extra: dev
Requires-Dist: pytest ; extra == 'dev'
Requires-Dist: pytest-flake8 ; extra == 'dev'
Requires-Dist: pytest-cov ; extra == 'dev'
Requires-Dist: pytest-mypy ; extra == 'dev'
Requires-Dist: pytest-pydocstyle ; extra == 'dev'
Requires-Dist: pytest-asyncio ; extra == 'dev'
Requires-Dist: mypy ; extra == 'dev'
Requires-Dist: pydocstyle ; extra == 'dev'
Requires-Dist: flake8 (<5.0.0) ; extra == 'dev'
Requires-Dist: pep8-naming ; extra == 'dev'
Provides-Extra: widgets
Requires-Dist: kornia ; extra == 'widgets'
Requires-Dist: torch ; extra == 'widgets'
Requires-Dist: numpy ; extra == 'widgets'
Requires-Dist: visdom ; extra == 'widgets'
Requires-Dist: opencv-python ; extra == 'widgets'
